digital_life/__init__.py
digital_life/log.py
digital_life/model_public.py
digital_life/redis_.py
digital_life/core/__init__.py
digital_life/core/biography2.py
digital_life/core/chat.py
digital_life/core/digital_avatar.py
digital_life/core/memorycard.py
digital_life/core/user.py
digital_life/core/recommend/embedding_model.py
digital_life/core/recommend/embedding_pool.py
digital_life/core/recommend/recommend.py
digital_life/server/__main__.py
digital_life/server/router/__init__.py
digital_life/server/router/biography.py
digital_life/server/router/chat.py
digital_life/server/router/chat_models.py
digital_life/server/router/digital_avatar.py
digital_life/server/router/memorycard.py
digital_life/server/router/recommend copy.py
digital_life/server/router/recommend.py
digital_life/server/router/user.py
digital_life-0.2.57.dist-info/METADATA
digital_life-0.2.57.dist-info/WHEEL
digital_life-0.2.57.dist-info/top_level.txt
digital_life-0.2.57.dist-info/RECORD
