Metadata-Version: 2.4
Name: digital-life
Version: 0.2.57
Summary: Add your description here
Requires-Python: >=3.12
Requires-Dist: anyio>=4.11.0
Requires-Dist: colorlog>=6.10.1
Requires-Dist: fastapi>=0.119.1
Requires-Dist: llama-index==0.12.30
Requires-Dist: llama-index-vector-stores-qdrant==0.6.1
Requires-Dist: qdrant-client==1.15.1
Requires-Dist: nbformat>=5.10.4
Requires-Dist: plotly>=6.3.1
Requires-Dist: redis>=7.0.0
Requires-Dist: rq>=2.6.0
Requires-Dist: termcolor>=3.2.0
Requires-Dist: uvicorn>=0.38.0
Requires-Dist: volcengine-python-sdk==4.0.6
